{
  "slug": "teen-side-hustle-tools-offline",
  "article_title": "Teen Side Hustle Tools Offline",
  "image": {
    "source": "pexels",
    "source_url": "https://www.pexels.com/photo/a-boy-in-black-hoodie-using-a-phone-and-a-laptop-9822679/",
    "photographer": "Atlantic Ambience",
    "photographer_url": "https://www.pexels.com/@freestockpro",
    "description": "Teenage boy using a phone and laptop, engaging in multitasking indoors.",
    "original_dimensions": "6000x4000"
  },
  "license": {
    "name": "Pexels License \u2014 free for commercial use, no attribution required",
    "url": "https://www.pexels.com/license/",
    "commercial_use": true,
    "attribution_required": false
  },
  "search_queries_used": [
    "teen working on laptop offline",
    "private data security concept",
    "sunset bedroom side hustle setup"
  ],
  "downloaded_at": "2026-04-02T00:14:54Z"
}